Metadata-Version: 2.1
Name: distributionsx
Version: 3.0
Summary: A package to calculate distributions (normal or binomial) sum, plot, mean and standard deviation.
Home-page: UNKNOWN
Author: Sidra Muntaha
Author-email: codehappysf@gmail.com
License: UNKNOWN
Platform: UNKNOWN
Classifier: Programming Language :: Python :: 3
Classifier: License :: OSI Approved :: MIT License
Classifier: Operating System :: OS Independent
Requires-Python: >=3.6
